<fest:template xmlns:fest="http://fest.mail.ru">
    <div class="navbar">
        <img class="navbar-icon" data-href="/" title="Домой" src="../img/home.svg"/>
        <img class="main_logo" data-href="/" src="../img/tabutask_logo_white.svg"/>
        <img id="avatarMini" class="avatar-mini" title="Профиль" src=""/>
    </div>
    <div id="myDropdown" class="dropdown-content">
        <a id="navbarSettings" href="/settings">Настройки</a>
        <a id="navbarLogout" href="">Выйти</a>
    </div>
</fest:template>
